atomd/__init__.py
atomd/lexer/__init__.py
atomd/parsers/__init__.py
atomd/parsers/html.py
tests/__init__.py
tests/helpers.py
tests/test_lexicon_values.py
tests/test_skeleton.py
tests/test_tokenize_bold.py
tests/test_tokenize_codeblock.py
tests/test_tokenize_escapes.py
tests/test_tokenize_headers.py
tests/test_tokenize_hyperlink.py
tests/test_tokenize_image_link.py
tests/test_tokenize_inline_code.py
tests/test_tokenize_italicize.py
tests/test_tokenize_lists.py
tests/test_tokenize_paragraphs.py
tests/test_tokenize_quote.py
tests/test_tokenize_whitespace.py
atomd-0.2.5.dist-info/LICENSE
atomd-0.2.5.dist-info/METADATA
atomd-0.2.5.dist-info/WHEEL
atomd-0.2.5.dist-info/top_level.txt
atomd-0.2.5.dist-info/RECORD
