Metadata-Version: 2.1
Name: atomd
Version: 0.2.5
Summary: A markdown lexer and parser which gives the programmer atomic control over markdown parsing.
Home-page: https://github.com/stonepresto/atomd
Author: stonepresto
Author-email: stonepresto@darkbyte.io
License: GPLv3
Project-URL: Bug Tracker, https://github.com/stonepresto/atomd/issues
Platform: UNKNOWN
Classifier: License :: OSI Approved :: GNU General Public License v3 (GPLv3)
Classifier: Programming Language :: Python :: 3
Classifier: Operating System :: OS Independent
Requires-Python: >=3.6
